pyob/__init__.py
pyob/exceptions/__init__.py
pyob/main/__init__.py
pyob/main/classes.py
pyob/main/tools/__init__.py
pyob/main/tools/index.py
pyob/main/tools/localize.py
pyob/main/tools/pyob_attr.py
pyob/main/tools/traverse.py
pyob/main/tools/validate.py
pyob/meta/__init__.py
pyob/meta/classes/__init__.py
pyob/meta/classes/metaclass.py
pyob/meta/classes/metaclass_base.py
pyob/set/__init__.py
pyob/set/classes.py
pyob/store/__init__.py
pyob/store/classes.py
pyob/tools/__init__.py
pyob/tools/iterable.py
pyob/tools/object.py
pyob/tools/string.py
pyob/utils/__init__.py
pyob-1.0.3.dist-info/LICENSE
pyob-1.0.3.dist-info/WHEEL
pyob-1.0.3.dist-info/METADATA
pyob-1.0.3.dist-info/RECORD
