Metadata-Version: 2.1
Name: pyob
Version: 1.0.3
Summary: A high-level runtime object manager for Python 3 and above.
License: MIT
Author: khunspoonzi
Author-email: khunspoonzi@gmail.com
Requires-Python: >=3.8,<4.0
Classifier: License :: OSI Approved :: MIT License
Classifier: Programming Language :: Python :: 3
Classifier: Programming Language :: Python :: 3.10
Classifier: Programming Language :: Python :: 3.8
Classifier: Programming Language :: Python :: 3.9
Requires-Dist: beartype (>=0.10.4,<0.11.0)
